nscholia/__init__.py
nscholia/backend.py
nscholia/backend_dashboard.py
nscholia/cmd.py
nscholia/dashboard.py
nscholia/endpoint_dashboard.py
nscholia/endpoints.py
nscholia/examples_dashboard.py
nscholia/google_sheet.py
nscholia/monitor.py
nscholia/version.py
nscholia/webserver.py
nscholia_examples/backends.yaml
nscholia_examples/dashboard_queries.yaml
nicescholia-0.0.4.dist-info/METADATA
nicescholia-0.0.4.dist-info/WHEEL
nicescholia-0.0.4.dist-info/entry_points.txt
nicescholia-0.0.4.dist-info/licenses/LICENSE
nicescholia-0.0.4.dist-info/RECORD
