Metadata-Version: 2.4
Name: nicescholia
Version: 0.0.4
Summary: nicegui based Scholia
Project-URL: Home, https://github.com/WolfgangFahl/nicescholia
Author-email: Wolfgang Fahl <wf@bitplan.com>
License-Expression: Apache-2.0
License-File: LICENSE
Classifier: Development Status :: 4 - Beta
Classifier: Environment :: Web Environment
Classifier: Intended Audience :: Developers
Classifier: Intended Audience :: Education
Classifier: Intended Audience :: Science/Research
Classifier: License :: OSI Approved :: Apache Software License
Classifier: Operating System :: OS Independent
Classifier: Programming Language :: Python :: 3 :: Only
Classifier: Programming Language :: Python :: 3.10
Classifier: Programming Language :: Python :: 3.11
Classifier: Programming Language :: Python :: 3.12
Classifier: Programming Language :: Python :: 3.13
Classifier: Topic :: Software Development :: User Interfaces
Requires-Python: >=3.11
Requires-Dist: httpx>=0.27.0
Requires-Dist: ngwidgets>=0.30.3
Requires-Dist: pandas>=2.3.3
Requires-Dist: pybasemkit>=0.1.6
Requires-Dist: snapquery>=0.2.5
